aws_config/__init__.py
aws_config/_version.py
aws_config/api.py
aws_config/config.py
aws_config/constants.py
aws_config/env.py
aws_config/exc.py
aws_config/logger.py
aws_config/paths.py
aws_config/s3.py
aws_config/utils.py
aws_config/vendor/__init__.py
aws_config/vendor/jsonutils.py
aws_config/vendor/pytest_cov_helper.py
aws_config/vendor/strutils.py
aws_config-0.1.4.dist-info/AUTHORS.rst
aws_config-0.1.4.dist-info/LICENSE.txt
aws_config-0.1.4.dist-info/METADATA
aws_config-0.1.4.dist-info/WHEEL
aws_config-0.1.4.dist-info/RECORD
