Metadata-Version: 2.3
Name: aws_config
Version: 0.1.4
Summary: A type-safe hierarchical configuration management system for AWS projects that provides environment-specific inheritance, validation, and integrated deployment to AWS SSM Parameter Store and S3 with custom versioning.
License: MIT
Author: Sanhe Hu
Author-email: husanhe@email.com
Maintainer: Sanhe Hu
Maintainer-email: husanhe@email.com
Requires-Python: >=3.10,<4.0
Classifier: License :: OSI Approved :: MIT License
Classifier: Programming Language :: Python :: 3
Classifier: Programming Language :: Python :: 3.10
Classifier: Programming Language :: Python :: 3.11
Classifier: Programming Language :: Python :: 3.12
Classifier: Programming Language :: Python :: 3.13
Provides-Extra: auto
Provides-Extra: dev
Provides-Extra: doc
Provides-Extra: test
Requires-Dist: Sphinx (>=7.4.7,<8.0.0) ; extra == "doc"
Requires-Dist: boto3 (>=1.35.99,<2.0.0)
Requires-Dist: boto3-stubs[s3,ssm] (>=1.35.99,<2.0.0) ; extra == "dev"
Requires-Dist: boto_session_manager (>=1.8.1,<2.0.0)
Requires-Dist: build (>=1.2.1,<2.0.0) ; extra == "dev"
Requires-Dist: configcraft (>=0.1.2,<1.0.0)
Requires-Dist: docfly (==3.0.0) ; extra == "doc"
Requires-Dist: enum-mate (>=0.1.1,<1.0.0)
Requires-Dist: furo (==2024.8.6) ; extra == "doc"
Requires-Dist: ipython (>=8.18.1,<8.19.0) ; extra == "doc"
Requires-Dist: moto (>=5.1.10,<6.0.0) ; extra == "test"
Requires-Dist: nbsphinx (>=0.8.12,<1.0.0) ; extra == "doc"
Requires-Dist: pydantic (>=2.11.0,<3.0.0)
Requires-Dist: pygments (>=2.18.0,<3.0.0) ; extra == "doc"
Requires-Dist: pytest (>=8.2.2,<9.0.0) ; extra == "test"
Requires-Dist: pytest-cov (>=6.0.0,<7.0.0) ; extra == "test"
Requires-Dist: rich (>=13.8.1,<14.0.0) ; extra == "dev"
Requires-Dist: rstobj (==1.2.1) ; extra == "doc"
Requires-Dist: s3pathlib (>=2.3.4,<3.0.0)
Requires-Dist: simple-aws-ssm-parameter-store (>=0.2.3,<1.0.0)
Requires-Dist: sphinx-copybutton (>=0.5.2,<1.0.0) ; extra == "doc"
Requires-Dist: sphinx-design (>=0.6.1,<1.0.0) ; extra == "doc"
Requires-Dist: sphinx-jinja (>=2.0.2,<3.0.0) ; extra == "doc"
Requires-Dist: twine (>=6.0.0,<7.0.0) ; extra == "dev"
Requires-Dist: typing-extensions (>=4.0.0,<5.0.0)
Requires-Dist: vislog (>=0.1.2,<1.0.0)
Requires-Dist: wheel (>=0.45.0,<1.0.0) ; extra == "dev"
Requires-Dist: which_bsm (>=0.1.1,<1.0.0)
Requires-Dist: which_env (>=0.1.1,<1.0.0)
Requires-Dist: which_runtime (>=0.1.1,<1.0.0)
Project-URL: Changelog, https://github.com/MacHu-GWU/aws_config-project/blob/main/release-history.rst
Project-URL: Documentation, https://aws-config.readthedocs.io/en/latest/
Project-URL: Download, https://pypi.org/pypi/aws-config#files
Project-URL: Homepage, https://github.com/MacHu-GWU/aws_config-project
Project-URL: Issues, https://github.com/MacHu-GWU/aws_config-project/issues
Project-URL: Repository, https://github.com/MacHu-GWU/aws_config-project
